http_request_codegen/__init__.py
http_request_codegen/hrc_api.py
http_request_codegen/hrc_exceptions.py
http_request_codegen/hrc_factory.py
http_request_codegen/hrc_http.py
http_request_codegen/hrc_meta.py
http_request_codegen/hrc_string.py
http_request_codegen/hrc_support.py
http_request_codegen/hrc_valuer.py
http_request_codegen-0.1.0.dist-info/LICENSE
http_request_codegen-0.1.0.dist-info/METADATA
http_request_codegen-0.1.0.dist-info/WHEEL
http_request_codegen-0.1.0.dist-info/top_level.txt
http_request_codegen-0.1.0.dist-info/RECORD
